Workbook

Sheet Inputs
A1: Email Input
A4: Field | B4: Value
A5: Subject | B5: Urgent: Payment Required Immediately
A6: Body | B6: Dear Customer, Your account shows an overdue balance. To avoid service suspension, please make payment within 12 hours. Click here to settle your account: bank@official.bank.com Failure to comply will result in permanent account closure. Sincerely, Billing Department
A8: Formula Name | B8: Formula Display | C8: Meaning
A9: Bayes theorem | B9: General: P(class | features) = [P(features | class) * P(class)] / P(features) Fraud: P(fraud | features) = [P(features | fraud) * P(fraud)] / P(features) Injection: P(injection | features) = [P(features | injection) * P(injection)] / P(features) Safe: P(safe | features) = [P(features | safe) * P(safe)] / P(features) | C9: Posterior probability after observing features X.
A10: Naive Bayes likelihood | B10: P(features | fraud) = product_i P(token_i | fraud) P(features | injection) = product_i P(token_i | injection) P(features | safe) = product_i P(token_i | safe) | C10: The project uses log form for numerical stability.
A11: Laplace smoothing | B11: log_score(fraud) = ln(P(fraud)) + sum_i count(token_i) * ln(P(token_i | fraud)) log_score(injection) = ln(P(injection)) + sum_i count(token_i) * ln(P(token_i | injection)) log_score(safe) = ln(P(safe)) + sum_i count(token_i) * ln(P(token_i | safe)) | C11: Prevents zero probabilities for unseen features.
A12: Log scoring | B12: P(token | fraud) = (freq(token,fraud)+alpha)/(token_total(fraud)+alpha*|V|) P(token | injection) = (freq(token,injection)+alpha)/(token_total(injection)+alpha*|V|) P(token | safe) = (freq(token,safe)+alpha)/(token_total(safe)+alpha*|V|) | C12: Raw scores used to choose the predicted label.
A13: Temperature softmax | B13: logit(fraud)=log_score(fraud)/token_count logit(injection)=log_score(injection)/token_count logit(safe)=log_score(safe)/token_count | C13: Final UI probabilities shown by the project.

Sheet Model Parameters
A1: Model Parameters From Dataset
A4: Parameter | B4: Fraud | C4: Injection | D4: Safe | E4: Formula / Meaning
A5: Class document count | B5: 3333 | C5: 3333 | D5: 3334 | E5: class_count(C_k)
A6: Total documents | B6: 10000 | C6: 10000 | D6: 10000 | E6: sum of all class document counts
A7: Class prior P(C_k) | B7: =B5/B6 -> 0.3333 | C7: =C5/C6 -> 0.3333 | D7: =D5/D6 -> 0.3334 | E7: P(fraud)=fraud_count/total_docs; P(injection)=injection_count/total_docs; P(safe)=safe_count/total_docs
A8: ln prior | B8: =LN(B7) -> -1.0987123 | C8: =LN(C7) -> -1.0987123 | D8: =LN(D7) -> -1.0984123 | E8: ln(P(fraud)), ln(P(injection)), ln(P(safe))
A9: Class token total | B9: 1168629 | C9: 879465 | D9: 219954 | E9: sum of feature counts in each class
A10: Vocabulary size |V| | B10: 6874 | C10: 6874 | D10: 6874 | E10: unique training features
A11: Laplace alpha | B11: 1 | C11: 1 | D11: 1 | E11: alpha
A12: Posterior temperature T | B12: 0.2 | C12: 0.2 | D12: 0.2 | E12: temperature used by softmax
A13: Keyword weight | B13: 10 | C13: 10 | D13: 10 | E13: fraud/injection keyword synthetic feature weight

Sheet Keyword Influence
A1: Keyword Influence
A4: Keyword | B4: Category | C4: Matched? | D4: Adds __fraud_kw__ | E4: Adds __injection_kw__ | F4: Adds __malicious_signal__ | G4: Formula shown
A5: account | B5: fraud | C5: =--ISNUMBER(SEARCH(A5,LOWER(Inputs!$B$5&" "&Inputs!$B$6))) -> TRUE | D5: 2 | E5: =IF(AND(B5="injection",C5=1),'Model Parameters'!$C$13,0) -> 0 | F5: 2 | G5: matched? = ISNUMBER(SEARCH(keyword, subject & body)); synthetic_count += keyword_weight
A6: account closure | B6: fraud | C6: =--ISNUMBER(SEARCH(A6,LOWER(Inputs!$B$5&" "&Inputs!$B$6))) -> TRUE | D6: 2 | E6: =IF(AND(B6="injection",C6=1),'Model Parameters'!$C$13,0) -> 0 | F6: 2 | G6: matched? = ISNUMBER(SEARCH(keyword, subject & body)); synthetic_count += keyword_weight
A7: account locked | B7: fraud | C7: =--ISNUMBER(SEARCH(A7,LOWER(Inputs!$B$5&" "&Inputs!$B$6))) -> FALSE | D7: =IF(AND(B7="fraud",C7=1),'Model Parameters'!$B$13,0) -> 0 | E7: =IF(AND(B7="injection",C7=1),'Model Parameters'!$C$13,0) -> 0 | F7: =IF(C7=1,IF(B7="fraud",'Model Parameters'!$B$13,'Model Parameters'!$C$13),0) -> 0 | G7: matched? = ISNUMBER(SEARCH(keyword, subject & body)); synthetic_count += keyword_weight
A8: account verification | B8: fraud | C8: =--ISNUMBER(SEARCH(A8,LOWER(Inputs!$B$5&" "&Inputs!$B$6))) -> FALSE | D8: =IF(AND(B8="fraud",C8=1),'Model Parameters'!$B$13,0) -> 0 | E8: =IF(AND(B8="injection",C8=1),'Model Parameters'!$C$13,0) -> 0 | F8: =IF(C8=1,IF(B8="fraud",'Model Parameters'!$B$13,'Model Parameters'!$C$13),0) -> 0 | G8: matched? = ISNUMBER(SEARCH(keyword, subject & body)); synthetic_count += keyword_weight
A9: act now | B9: fraud | C9: =--ISNUMBER(SEARCH(A9,LOWER(Inputs!$B$5&" "&Inputs!$B$6))) -> FALSE | D9: =IF(AND(B9="fraud",C9=1),'Model Parameters'!$B$13,0) -> 0 | E9: =IF(AND(B9="injection",C9=1),'Model Parameters'!$C$13,0) -> 0 | F9: =IF(C9=1,IF(B9="fraud",'Model Parameters'!$B$13,'Model Parameters'!$C$13),0) -> 0 | G9: matched? = ISNUMBER(SEARCH(keyword, subject & body)); synthetic_count += keyword_weight
A10: action | B10: fraud | C10: =--ISNUMBER(SEARCH(A10,LOWER(Inputs!$B$5&" "&Inputs!$B$6))) -> FALSE | D10: =IF(AND(B10="fraud",C10=1),'Model Parameters'!$B$13,0) -> 0 | E10: =IF(AND(B10="injection",C10=1),'Model Parameters'!$C$13,0) -> 0 | F10: =IF(C10=1,IF(B10="fraud",'Model Parameters'!$B$13,'Model Parameters'!$C$13),0) -> 0 | G10: matched? = ISNUMBER(SEARCH(keyword, subject & body)); synthetic_count += keyword_weight
A11: activity | B11: fraud | C11: =--ISNUMBER(SEARCH(A11,LOWER(Inputs!$B$5&" "&Inputs!$B$6))) -> FALSE | D11: =IF(AND(B11="fraud",C11=1),'Model Parameters'!$B$13,0) -> 0 | E11: =IF(AND(B11="injection",C11=1),'Model Parameters'!$C$13,0) -> 0 | F11: =IF(C11=1,IF(B11="fraud",'Model Parameters'!$B$13,'Model Parameters'!$C$13),0) -> 0 | G11: matched? = ISNUMBER(SEARCH(keyword, subject & body)); synthetic_count += keyword_weight
A12: alert | B12: fraud | C12: =--ISNUMBER(SEARCH(A12,LOWER(Inputs!$B$5&" "&Inputs!$B$6))) -> FALSE | D12: =IF(AND(B12="fraud",C12=1),'Model Parameters'!$B$13,0) -> 0 | E12: =IF(AND(B12="injection",C12=1),'Model Parameters'!$C$13,0) -> 0 | F12: =IF(C12=1,IF(B12="fraud",'Model Parameters'!$B$13,'Model Parameters'!$C$13),0) -> 0 | G12: matched? = ISNUMBER(SEARCH(keyword, subject & body)); synthetic_count += keyword_weight
A13: amazon | B13: fraud | C13: =--ISNUMBER(SEARCH(A13,LOWER(Inputs!$B$5&" "&Inputs!$B$6))) -> FALSE | D13: =IF(AND(B13="fraud",C13=1),'Model Parameters'!$B$13,0) -> 0 | E13: =IF(AND(B13="injection",C13=1),'Model Parameters'!$C$13,0) -> 0 | F13: =IF(C13=1,IF(B13="fraud",'Model Parameters'!$B$13,'Model Parameters'!$C$13),0) -> 0 | G13: matched? = ISNUMBER(SEARCH(keyword, subject & body)); synthetic_count += keyword_weight
A14: apple | B14: fraud | C14: =--ISNUMBER(SEARCH(A14,LOWER(Inputs!$B$5&" "&Inputs!$B$6))) -> FALSE | D14: =IF(AND(B14="fraud",C14=1),'Model Parameters'!$B$13,0) -> 0 | E14: =IF(AND(B14="injection",C14=1),'Model Parameters'!$C$13,0) -> 0 | F14: =IF(C14=1,IF(B14="fraud",'Model Parameters'!$B$13,'Model Parameters'!$C$13),0) -> 0 | G14: matched? = ISNUMBER(SEARCH(keyword, subject & body)); synthetic_count += keyword_weight
A15: bank | B15: fraud | C15: =--ISNUMBER(SEARCH(A15,LOWER(Inputs!$B$5&" "&Inputs!$B$6))) -> TRUE | D15: 2 | E15: =IF(AND(B15="injection",C15=1),'Model Parameters'!$C$13,0) -> 0 | F15: 2 | G15: matched? = ISNUMBER(SEARCH(keyword, subject & body)); synthetic_count += keyword_weight
A16: bank details | B16: fraud | C16: =--ISNUMBER(SEARCH(A16,LOWER(Inputs!$B$5&" "&Inputs!$B$6))) -> FALSE | D16: =IF(AND(B16="fraud",C16=1),'Model Parameters'!$B$13,0) -> 0 | E16: =IF(AND(B16="injection",C16=1),'Model Parameters'!$C$13,0) -> 0 | F16: =IF(C16=1,IF(B16="fraud",'Model Parameters'!$B$13,'Model Parameters'!$C$13),0) -> 0 | G16: matched? = ISNUMBER(SEARCH(keyword, subject & body)); synthetic_count += keyword_weight
A17: billing | B17: fraud | C17: =--ISNUMBER(SEARCH(A17,LOWER(Inputs!$B$5&" "&Inputs!$B$6))) -> TRUE | D17: 2 | E17: =IF(AND(B17="injection",C17=1),'Model Parameters'!$C$13,0) -> 0 | F17: 2 | G17: matched? = ISNUMBER(SEARCH(keyword, subject & body)); synthetic_count += keyword_weight
A18: card declined | B18: fraud | C18: =--ISNUMBER(SEARCH(A18,LOWER(Inputs!$B$5&" "&Inputs!$B$6))) -> FALSE | D18: =IF(AND(B18="fraud",C18=1),'Model Parameters'!$B$13,0) -> 0 | E18: =IF(AND(B18="injection",C18=1),'Model Parameters'!$C$13,0) -> 0 | F18: =IF(C18=1,IF(B18="fraud",'Model Parameters'!$B$13,'Model Parameters'!$C$13),0) -> 0 | G18: matched? = ISNUMBER(SEARCH(keyword, subject & body)); synthetic_count += keyword_weight
A19: cash prize | B19: fraud | C19: =--ISNUMBER(SEARCH(A19,LOWER(Inputs!$B$5&" "&Inputs!$B$6))) -> FALSE | D19: =IF(AND(B19="fraud",C19=1),'Model Parameters'!$B$13,0) -> 0 | E19: =IF(AND(B19="injection",C19=1),'Model Parameters'!$C$13,0) -> 0 | F19: =IF(C19=1,IF(B19="fraud",'Model Parameters'!$B$13,'Model Parameters'!$C$13),0) -> 0 | G19: matched? = ISNUMBER(SEARCH(keyword, subject & body)); synthetic_count += keyword_weight
A20: claim | B20: fraud | C20: =--ISNUMBER(SEARCH(A20,LOWER(Inputs!$B$5&" "&Inputs!$B$6))) -> FALSE | D20: =IF(AND(B20="fraud",C20=1),'Model Parameters'!$B$13,0) -> 0 | E20: =IF(AND(B20="injection",C20=1),'Model Parameters'!$C$13,0) -> 0 | F20: =IF(C20=1,IF(B20="fraud",'Model Parameters'!$B$13,'Model Parameters'!$C$13),0) -> 0 | G20: matched? = ISNUMBER(SEARCH(keyword, subject & body)); synthetic_count += keyword_weight
A21: claim reward | B21: fraud | C21: =--ISNUMBER(SEARCH(A21,LOWER(Inputs!$B$5&" "&Inputs!$B$6))) -> FALSE | D21: =IF(AND(B21="fraud",C21=1),'Model Parameters'!$B$13,0) -> 0 | E21: =IF(AND(B21="injection",C21=1),'Model Parameters'!$C$13,0) -> 0 | F21: =IF(C21=1,IF(B21="fraud",'Model Parameters'!$B$13,'Model Parameters'!$C$13),0) -> 0 | G21: matched? = ISNUMBER(SEARCH(keyword, subject & body)); synthetic_count += keyword_weight
A22: click | B22: fraud | C22: =--ISNUMBER(SEARCH(A22,LOWER(Inputs!$B$5&" "&Inputs!$B$6))) -> TRUE | D22: 2 | E22: =IF(AND(B22="injection",C22=1),'Model Parameters'!$C$13,0) -> 0 | F22: 2 | G22: matched? = ISNUMBER(SEARCH(keyword, subject & body)); synthetic_count += keyword_weight
A23: click here | B23: fraud | C23: =--ISNUMBER(SEARCH(A23,LOWER(Inputs!$B$5&" "&Inputs!$B$6))) -> TRUE | D23: 2 | E23: =IF(AND(B23="injection",C23=1),'Model Parameters'!$C$13,0) -> 0 | F23: 2 | G23: matched? = ISNUMBER(SEARCH(keyword, subject & body)); synthetic_count += keyword_weight
A24: confirm | B24: fraud | C24: =--ISNUMBER(SEARCH(A24,LOWER(Inputs!$B$5&" "&Inputs!$B$6))) -> FALSE | D24: =IF(AND(B24="fraud",C24=1),'Model Parameters'!$B$13,0) -> 0 | E24: =IF(AND(B24="injection",C24=1),'Model Parameters'!$C$13,0) -> 0 | F24: =IF(C24=1,IF(B24="fraud",'Model Parameters'!$B$13,'Model Parameters'!$C$13),0) -> 0 | G24: matched? = ISNUMBER(SEARCH(keyword, subject & body)); synthetic_count += keyword_weight
A25: confirm account | B25: fraud | C25: =--ISNUMBER(SEARCH(A25,LOWER(Inputs!$B$5&" "&Inputs!$B$6))) -> FALSE | D25: =IF(AND(B25="fraud",C25=1),'Model Parameters'!$B$13,0) -> 0 | E25: =IF(AND(B25="injection",C25=1),'Model Parameters'!$C$13,0) -> 0 | F25: =IF(C25=1,IF(B25="fraud",'Model Parameters'!$B$13,'Model Parameters'!$C$13),0) -> 0 | G25: matched? = ISNUMBER(SEARCH(keyword, subject & body)); synthetic_count += keyword_weight
A26: confirm identity | B26: fraud | C26: =--ISNUMBER(SEARCH(A26,LOWER(Inputs!$B$5&" "&Inputs!$B$6))) -> FALSE | D26: =IF(AND(B26="fraud",C26=1),'Model Parameters'!$B$13,0) -> 0 | E26: =IF(AND(B26="injection",C26=1),'Model Parameters'!$C$13,0) -> 0 | F26: =IF(C26=1,IF(B26="fraud",'Model Parameters'!$B$13,'Model Parameters'!$C$13),0) -> 0 | G26: matched? = ISNUMBER(SEARCH(keyword, subject & body)); synthetic_count += keyword_weight
A27: confirm payment | B27: fraud | C27: =--ISNUMBER(SEARCH(A27,LOWER(Inputs!$B$5&" "&Inputs!$B$6))) -> FALSE | D27: =IF(AND(B27="fraud",C27=1),'Model Parameters'!$B$13,0) -> 0 | E27: =IF(AND(B27="injection",C27=1),'Model Parameters'!$C$13,0) -> 0 | F27: =IF(C27=1,IF(B27="fraud",'Model Parameters'!$B$13,'Model Parameters'!$C$13),0) -> 0 | G27: matched? = ISNUMBER(SEARCH(keyword, subject & body)); synthetic_count += keyword_weight
A28: congratulations | B28: fraud | C28: =--ISNUMBER(SEARCH(A28,LOWER(Inputs!$B$5&" "&Inputs!$B$6))) -> FALSE | D28: =IF(AND(B28="fraud",C28=1),'Model Parameters'!$B$13,0) -> 0 | E28: =IF(AND(B28="injection",C28=1),'Model Parameters'!$C$13,0) -> 0 | F28: =IF(C28=1,IF(B28="fraud",'Model Parameters'!$B$13,'Model Parameters'!$C$13),0) -> 0 | G28: matched? = ISNUMBER(SEARCH(keyword, subject & body)); synthetic_count += keyword_weight
A29: credential | B29: fraud | C29: =--ISNUMBER(SEARCH(A29,LOWER(Inputs!$B$5&" "&Inputs!$B$6))) -> FALSE | D29: =IF(AND(B29="fraud",C29=1),'Model Parameters'!$B$13,0) -> 0 | E29: =IF(AND(B29="injection",C29=1),'Model Parameters'!$C$13,0) -> 0 | F29: =IF(C29=1,IF(B29="fraud",'Model Parameters'!$B$13,'Model Parameters'!$C$13),0) -> 0 | G29: matched? = ISNUMBER(SEARCH(keyword, subject & body)); synthetic_count += keyword_weight
A30: crypto | B30: fraud | C30: =--ISNUMBER(SEARCH(A30,LOWER(Inputs!$B$5&" "&Inputs!$B$6))) -> FALSE | D30: =IF(AND(B30="fraud",C30=1),'Model Parameters'!$B$13,0) -> 0 | E30: =IF(AND(B30="injection",C30=1),'Model Parameters'!$C$13,0) -> 0 | F30: =IF(C30=1,IF(B30="fraud",'Model Parameters'!$B$13,'Model Parameters'!$C$13),0) -> 0 | G30: matched? = ISNUMBER(SEARCH(keyword, subject & body)); synthetic_count += keyword_weight
A31: customs fee | B31: fraud | C31: =--ISNUMBER(SEARCH(A31,LOWER(Inputs!$B$5&" "&Inputs!$B$6))) -> FALSE | D31: =IF(AND(B31="fraud",C31=1),'Model Parameters'!$B$13,0) -> 0 | E31: =IF(AND(B31="injection",C31=1),'Model Parameters'!$C$13,0) -> 0 | F31: =IF(C31=1,IF(B31="fraud",'Model Parameters'!$B$13,'Model Parameters'!$C$13),0) -> 0 | G31: matched? = ISNUMBER(SEARCH(keyword, subject & body)); synthetic_count += keyword_weight
A32: deactivate account | B32: fraud | C32: =--ISNUMBER(SEARCH(A32,LOWER(Inputs!$B$5&" "&Inputs!$B$6))) -> FALSE | D32: =IF(AND(B32="fraud",C32=1),'Model Parameters'!$B$13,0) -> 0 | E32: =IF(AND(B32="injection",C32=1),'Model Parameters'!$C$13,0) -> 0 | F32: =IF(C32=1,IF(B32="fraud",'Model Parameters'!$B$13,'Model Parameters'!$C$13),0) -> 0 | G32: matched? = ISNUMBER(SEARCH(keyword, subject & body)); synthetic_count += keyword_weight
A33: deactivation | B33: fraud | C33: =--ISNUMBER(SEARCH(A33,LOWER(Inputs!$B$5&" "&Inputs!$B$6))) -> FALSE | D33: =IF(AND(B33="fraud",C33=1),'Model Parameters'!$B$13,0) -> 0 | E33: =IF(AND(B33="injection",C33=1),'Model Parameters'!$C$13,0) -> 0 | F33: =IF(C33=1,IF(B33="fraud",'Model Parameters'!$B$13,'Model Parameters'!$C$13),0) -> 0 | G33: matched? = ISNUMBER(SEARCH(keyword, subject & body)); synthetic_count += keyword_weight
A34: expire | B34: fraud | C34: =--ISNUMBER(SEARCH(A34,LOWER(Inputs!$B$5&" "&Inputs!$B$6))) -> FALSE | D34: =IF(AND(B34="fraud",C34=1),'Model Parameters'!$B$13,0) -> 0 | E34: =IF(AND(B34="injection",C34=1),'Model Parameters'!$C$13,0) -> 0 | F34: =IF(C34=1,IF(B34="fraud",'Model Parameters'!$B$13,'Model Parameters'!$C$13),0) -> 0 | G34: matched? = ISNUMBER(SEARCH(keyword, subject & body)); synthetic_count += keyword_weight
A35: failure to comply | B35: fraud | C35: =--ISNUMBER(SEARCH(A35,LOWER(Inputs!$B$5&" "&Inputs!$B$6))) -> TRUE | D35: 2 | E35: =IF(AND(B35="injection",C35=1),'Model Parameters'!$C$13,0) -> 0 | F35: 2 | G35: matched? = ISNUMBER(SEARCH(keyword, subject & body)); synthetic_count += keyword_weight
A36: final notice | B36: fraud | C36: =--ISNUMBER(SEARCH(A36,LOWER(Inputs!$B$5&" "&Inputs!$B$6))) -> FALSE | D36: =IF(AND(B36="fraud",C36=1),'Model Parameters'!$B$13,0) -> 0 | E36: =IF(AND(B36="injection",C36=1),'Model Parameters'!$C$13,0) -> 0 | F36: =IF(C36=1,IF(B36="fraud",'Model Parameters'!$B$13,'Model Parameters'!$C$13),0) -> 0 | G36: matched? = ISNUMBER(SEARCH(keyword, subject & body)); synthetic_count += keyword_weight
A37: final warning | B37: fraud | C37: =--ISNUMBER(SEARCH(A37,LOWER(Inputs!$B$5&" "&Inputs!$B$6))) -> FALSE | D37: =IF(AND(B37="fraud",C37=1),'Model Parameters'!$B$13,0) -> 0 | E37: =IF(AND(B37="injection",C37=1),'Model Parameters'!$C$13,0) -> 0 | F37: =IF(C37=1,IF(B37="fraud",'Model Parameters'!$B$13,'Model Parameters'!$C$13),0) -> 0 | G37: matched? = ISNUMBER(SEARCH(keyword, subject & body)); synthetic_count += keyword_weight
A38: fraud alert | B38: fraud | C38: =--ISNUMBER(SEARCH(A38,LOWER(Inputs!$B$5&" "&Inputs!$B$6))) -> FALSE | D38: =IF(AND(B38="fraud",C38=1),'Model Parameters'!$B$13,0) -> 0 | E38: =IF(AND(B38="injection",C38=1),'Model Parameters'!$C$13,0) -> 0 | F38: =IF(C38=1,IF(B38="fraud",'Model Parameters'!$B$13,'Model Parameters'!$C$13),0) -> 0 | G38: matched? = ISNUMBER(SEARCH(keyword, subject & body)); synthetic_count += keyword_weight
A39: gift card | B39: fraud | C39: =--ISNUMBER(SEARCH(A39,LOWER(Inputs!$B$5&" "&Inputs!$B$6))) -> FALSE | D39: =IF(AND(B39="fraud",C39=1),'Model Parameters'!$B$13,0) -> 0 | E39: =IF(AND(B39="injection",C39=1),'Model Parameters'!$C$13,0) -> 0 | F39: =IF(C39=1,IF(B39="fraud",'Model Parameters'!$B$13,'Model Parameters'!$C$13),0) -> 0 | G39: matched? = ISNUMBER(SEARCH(keyword, subject & body)); synthetic_count += keyword_weight
A40: identity | B40: fraud | C40: =--ISNUMBER(SEARCH(A40,LOWER(Inputs!$B$5&" "&Inputs!$B$6))) -> FALSE | D40: =IF(AND(B40="fraud",C40=1),'Model Parameters'!$B$13,0) -> 0 | E40: =IF(AND(B40="injection",C40=1),'Model Parameters'!$C$13,0) -> 0 | F40: =IF(C40=1,IF(B40="fraud",'Model Parameters'!$B$13,'Model Parameters'!$C$13),0) -> 0 | G40: matched? = ISNUMBER(SEARCH(keyword, subject & body)); synthetic_count += keyword_weight
A41: identity confirmation | B41: fraud | C41: =--ISNUMBER(SEARCH(A41,LOWER(Inputs!$B$5&" "&Inputs!$B$6))) -> FALSE | D41: =IF(AND(B41="fraud",C41=1),'Model Parameters'!$B$13,0) -> 0 | E41: =IF(AND(B41="injection",C41=1),'Model Parameters'!$C$13,0) -> 0 | F41: =IF(C41=1,IF(B41="fraud",'Model Parameters'!$B$13,'Model Parameters'!$C$13),0) -> 0 | G41: matched? = ISNUMBER(SEARCH(keyword, subject & body)); synthetic_count += keyword_weight
A42: immediate | B42: fraud | C42: =--ISNUMBER(SEARCH(A42,LOWER(Inputs!$B$5&" "&Inputs!$B$6))) -> TRUE | D42: 2 | E42: =IF(AND(B42="injection",C42=1),'Model Parameters'!$C$13,0) -> 0 | F42: 2 | G42: matched? = ISNUMBER(SEARCH(keyword, subject & body)); synthetic_count += keyword_weight
A43: immediately | B43: fraud | C43: =--ISNUMBER(SEARCH(A43,LOWER(Inputs!$B$5&" "&Inputs!$B$6))) -> TRUE | D43: 2 | E43: =IF(AND(B43="injection",C43=1),'Model Parameters'!$C$13,0) -> 0 | F43: 2 | G43: matched? = ISNUMBER(SEARCH(keyword, subject & body)); synthetic_count += keyword_weight
A44: invoice | B44: fraud | C44: =--ISNUMBER(SEARCH(A44,LOWER(Inputs!$B$5&" "&Inputs!$B$6))) -> FALSE | D44: =IF(AND(B44="fraud",C44=1),'Model Parameters'!$B$13,0) -> 0 | E44: =IF(AND(B44="injection",C44=1),'Model Parameters'!$C$13,0) -> 0 | F44: =IF(C44=1,IF(B44="fraud",'Model Parameters'!$B$13,'Model Parameters'!$C$13),0) -> 0 | G44: matched? = ISNUMBER(SEARCH(keyword, subject & body)); synthetic_count += keyword_weight
A45: last warning | B45: fraud | C45: =--ISNUMBER(SEARCH(A45,LOWER(Inputs!$B$5&" "&Inputs!$B$6))) -> FALSE | D45: =IF(AND(B45="fraud",C45=1),'Model Parameters'!$B$13,0) -> 0 | E45: =IF(AND(B45="injection",C45=1),'Model Parameters'!$C$13,0) -> 0 | F45: =IF(C45=1,IF(B45="fraud",'Model Parameters'!$B$13,'Model Parameters'!$C$13),0) -> 0 | G45: matched? = ISNUMBER(SEARCH(keyword, subject & body)); synthetic_count += keyword_weight
A46: legal action | B46: fraud | C46: =--ISNUMBER(SEARCH(A46,LOWER(Inputs!$B$5&" "&Inputs!$B$6))) -> FALSE | D46: =IF(AND(B46="fraud",C46=1),'Model Parameters'!$B$13,0) -> 0 | E46: =IF(AND(B46="injection",C46=1),'Model Parameters'!$C$13,0) -> 0 | F46: =IF(C46=1,IF(B46="fraud",'Model Parameters'!$B$13,'Model Parameters'!$C$13),0) -> 0 | G46: matched? = ISNUMBER(SEARCH(keyword, subject & body)); synthetic_count += keyword_weight
A47: limited opportunity | B47: fraud | C47: =--ISNUMBER(SEARCH(A47,LOWER(Inputs!$B$5&" "&Inputs!$B$6))) -> FALSE | D47: =IF(AND(B47="fraud",C47=1),'Model Parameters'!$B$13,0) -> 0 | E47: =IF(AND(B47="injection",C47=1),'Model Parameters'!$C$13,0) -> 0 | F47: =IF(C47=1,IF(B47="fraud",'Model Parameters'!$B$13,'Model Parameters'!$C$13),0) -> 0 | G47: matched? = ISNUMBER(SEARCH(keyword, subject & body)); synthetic_count += keyword_weight
A48: limited time | B48: fraud | C48: =--ISNUMBER(SEARCH(A48,LOWER(Inputs!$B$5&" "&Inputs!$B$6))) -> FALSE | D48: =IF(AND(B48="fraud",C48=1),'Model Parameters'!$B$13,0) -> 0 | E48: =IF(AND(B48="injection",C48=1),'Model Parameters'!$C$13,0) -> 0 | F48: =IF(C48=1,IF(B48="fraud",'Model Parameters'!$B$13,'Model Parameters'!$C$13),0) -> 0 | G48: matched? = ISNUMBER(SEARCH(keyword, subject & body)); synthetic_count += keyword_weight
A49: link | B49: fraud | C49: =--ISNUMBER(SEARCH(A49,LOWER(Inputs!$B$5&" "&Inputs!$B$6))) -> FALSE | D49: =IF(AND(B49="fraud",C49=1),'Model Parameters'!$B$13,0) -> 0 | E49: =IF(AND(B49="injection",C49=1),'Model Parameters'!$C$13,0) -> 0 | F49: =IF(C49=1,IF(B49="fraud",'Model Parameters'!$B$13,'Model Parameters'!$C$13),0) -> 0 | G49: matched? = ISNUMBER(SEARCH(keyword, subject & body)); synthetic_count += keyword_weight
A50: locked | B50: fraud | C50: =--ISNUMBER(SEARCH(A50,LOWER(Inputs!$B$5&" "&Inputs!$B$6))) -> FALSE | D50: =IF(AND(B50="fraud",C50=1),'Model Parameters'!$B$13,0) -> 0 | E50: =IF(AND(B50="injection",C50=1),'Model Parameters'!$C$13,0) -> 0 | F50: =IF(C50=1,IF(B50="fraud",'Model Parameters'!$B$13,'Model Parameters'!$C$13),0) -> 0 | G50: matched? = ISNUMBER(SEARCH(keyword, subject & body)); synthetic_count += keyword_weight
A51: login | B51: fraud | C51: =--ISNUMBER(SEARCH(A51,LOWER(Inputs!$B$5&" "&Inputs!$B$6))) -> FALSE | D51: =IF(AND(B51="fraud",C51=1),'Model Parameters'!$B$13,0) -> 0 | E51: =IF(AND(B51="injection",C51=1),'Model Parameters'!$C$13,0) -> 0 | F51: =IF(C51=1,IF(B51="fraud",'Model Parameters'!$B$13,'Model Parameters'!$C$13),0) -> 0 | G51: matched? = ISNUMBER(SEARCH(keyword, subject & body)); synthetic_count += keyword_weight
A52: login credentials | B52: fraud | C52: =--ISNUMBER(SEARCH(A52,LOWER(Inputs!$B$5&" "&Inputs!$B$6))) -> FALSE | D52: =IF(AND(B52="fraud",C52=1),'Model Parameters'!$B$13,0) -> 0 | E52: =IF(AND(B52="injection",C52=1),'Model Parameters'!$C$13,0) -> 0 | F52: =IF(C52=1,IF(B52="fraud",'Model Parameters'!$B$13,'Model Parameters'!$C$13),0) -> 0 | G52: matched? = ISNUMBER(SEARCH(keyword, subject & body)); synthetic_count += keyword_weight
A53: login now | B53: fraud | C53: =--ISNUMBER(SEARCH(A53,LOWER(Inputs!$B$5&" "&Inputs!$B$6))) -> FALSE | D53: =IF(AND(B53="fraud",C53=1),'Model Parameters'!$B$13,0) -> 0 | E53: =IF(AND(B53="injection",C53=1),'Model Parameters'!$C$13,0) -> 0 | F53: =IF(C53=1,IF(B53="fraud",'Model Parameters'!$B$13,'Model Parameters'!$C$13),0) -> 0 | G53: matched? = ISNUMBER(SEARCH(keyword, subject & body)); synthetic_count += keyword_weight
A54: microsoft | B54: fraud | C54: =--ISNUMBER(SEARCH(A54,LOWER(Inputs!$B$5&" "&Inputs!$B$6))) -> FALSE | D54: =IF(AND(B54="fraud",C54=1),'Model Parameters'!$B$13,0) -> 0 | E54: =IF(AND(B54="injection",C54=1),'Model Parameters'!$C$13,0) -> 0 | F54: =IF(C54=1,IF(B54="fraud",'Model Parameters'!$B$13,'Model Parameters'!$C$13),0) -> 0 | G54: matched? = ISNUMBER(SEARCH(keyword, subject & body)); synthetic_count += keyword_weight
A55: official notice | B55: fraud | C55: =--ISNUMBER(SEARCH(A55,LOWER(Inputs!$B$5&" "&Inputs!$B$6))) -> FALSE | D55: =IF(AND(B55="fraud",C55=1),'Model Parameters'!$B$13,0) -> 0 | E55: =IF(AND(B55="injection",C55=1),'Model Parameters'!$C$13,0) -> 0 | F55: =IF(C55=1,IF(B55="fraud",'Model Parameters'!$B$13,'Model Parameters'!$C$13),0) -> 0 | G55: matched? = ISNUMBER(SEARCH(keyword, subject & body)); synthetic_count += keyword_weight
A56: overdue | B56: fraud | C56: =--ISNUMBER(SEARCH(A56,LOWER(Inputs!$B$5&" "&Inputs!$B$6))) -> TRUE | D56: 2 | E56: =IF(AND(B56="injection",C56=1),'Model Parameters'!$C$13,0) -> 0 | F56: 2 | G56: matched? = ISNUMBER(SEARCH(keyword, subject & body)); synthetic_count += keyword_weight
A57: password | B57: fraud | C57: =--ISNUMBER(SEARCH(A57,LOWER(Inputs!$B$5&" "&Inputs!$B$6))) -> FALSE | D57: =IF(AND(B57="fraud",C57=1),'Model Parameters'!$B$13,0) -> 0 | E57: =IF(AND(B57="injection",C57=1),'Model Parameters'!$C$13,0) -> 0 | F57: =IF(C57=1,IF(B57="fraud",'Model Parameters'!$B$13,'Model Parameters'!$C$13),0) -> 0 | G57: matched? = ISNUMBER(SEARCH(keyword, subject & body)); synthetic_count += keyword_weight
A58: past due | B58: fraud | C58: =--ISNUMBER(SEARCH(A58,LOWER(Inputs!$B$5&" "&Inputs!$B$6))) -> FALSE | D58: =IF(AND(B58="fraud",C58=1),'Model Parameters'!$B$13,0) -> 0 | E58: =IF(AND(B58="injection",C58=1),'Model Parameters'!$C$13,0) -> 0 | F58: =IF(C58=1,IF(B58="fraud",'Model Parameters'!$B$13,'Model Parameters'!$C$13),0) -> 0 | G58: matched? = ISNUMBER(SEARCH(keyword, subject & body)); synthetic_count += keyword_weight
A59: payment | B59: fraud | C59: =--ISNUMBER(SEARCH(A59,LOWER(Inputs!$B$5&" "&Inputs!$B$6))) -> TRUE | D59: 2 | E59: =IF(AND(B59="injection",C59=1),'Model Parameters'!$C$13,0) -> 0 | F59: 2 | G59: matched? = ISNUMBER(SEARCH(keyword, subject & body)); synthetic_count += keyword_weight
A60: payment due | B60: fraud | C60: =--ISNUMBER(SEARCH(A60,LOWER(Inputs!$B$5&" "&Inputs!$B$6))) -> FALSE | D60: =IF(AND(B60="fraud",C60=1),'Model Parameters'!$B$13,0) -> 0 | E60: =IF(AND(B60="injection",C60=1),'Model Parameters'!$C$13,0) -> 0 | F60: =IF(C60=1,IF(B60="fraud",'Model Parameters'!$B$13,'Model Parameters'!$C$13),0) -> 0 | G60: matched? = ISNUMBER(SEARCH(keyword, subject & body)); synthetic_count += keyword_weight
A61: payment information | B61: fraud | C61: =--ISNUMBER(SEARCH(A61,LOWER(Inputs!$B$5&" "&Inputs!$B$6))) -> FALSE | D61: =IF(AND(B61="fraud",C61=1),'Model Parameters'!$B$13,0) -> 0 | E61: =IF(AND(B61="injection",C61=1),'Model Parameters'!$C$13,0) -> 0 | F61: =IF(C61=1,IF(B61="fraud",'Model Parameters'!$B$13,'Model Parameters'!$C$13),0) -> 0 | G61: matched? = ISNUMBER(SEARCH(keyword, subject & body)); synthetic_count += keyword_weight
A62: payment required | B62: fraud | C62: =--ISNUMBER(SEARCH(A62,LOWER(Inputs!$B$5&" "&Inputs!$B$6))) -> TRUE | D62: 2 | E62: =IF(AND(B62="injection",C62=1),'Model Parameters'!$C$13,0) -> 0 | F62: 2 | G62: matched? = ISNUMBER(SEARCH(keyword, subject & body)); synthetic_count += keyword_weight
A63: paypal | B63: fraud | C63: =--ISNUMBER(SEARCH(A63,LOWER(Inputs!$B$5&" "&Inputs!$B$6))) -> FALSE | D63: =IF(AND(B63="fraud",C63=1),'Model Parameters'!$B$13,0) -> 0 | E63: =IF(AND(B63="injection",C63=1),'Model Parameters'!$C$13,0) -> 0 | F63: =IF(C63=1,IF(B63="fraud",'Model Parameters'!$B$13,'Model Parameters'!$C$13),0) -> 0 | G63: matched? = ISNUMBER(SEARCH(keyword, subject & body)); synthetic_count += keyword_weight
A64: prize | B64: fraud | C64: =--ISNUMBER(SEARCH(A64,LOWER(Inputs!$B$5&" "&Inputs!$B$6))) -> FALSE | D64: =IF(AND(B64="fraud",C64=1),'Model Parameters'!$B$13,0) -> 0 | E64: =IF(AND(B64="injection",C64=1),'Model Parameters'!$C$13,0) -> 0 | F64: =IF(C64=1,IF(B64="fraud",'Model Parameters'!$B$13,'Model Parameters'!$C$13),0) -> 0 | G64: matched? = ISNUMBER(SEARCH(keyword, subject & body)); synthetic_count += keyword_weight
A65: processing fee | B65: fraud | C65: =--ISNUMBER(SEARCH(A65,LOWER(Inputs!$B$5&" "&Inputs!$B$6))) -> FALSE | D65: =IF(AND(B65="fraud",C65=1),'Model Parameters'!$B$13,0) -> 0 | E65: =IF(AND(B65="injection",C65=1),'Model Parameters'!$C$13,0) -> 0 | F65: =IF(C65=1,IF(B65="fraud",'Model Parameters'!$B$13,'Model Parameters'!$C$13),0) -> 0 | G65: matched? = ISNUMBER(SEARCH(keyword, subject & body)); synthetic_count += keyword_weight
A66: re-activate | B66: fraud | C66: =--ISNUMBER(SEARCH(A66,LOWER(Inputs!$B$5&" "&Inputs!$B$6))) -> FALSE | D66: =IF(AND(B66="fraud",C66=1),'Model Parameters'!$B$13,0) -> 0 | E66: =IF(AND(B66="injection",C66=1),'Model Parameters'!$C$13,0) -> 0 | F66: =IF(C66=1,IF(B66="fraud",'Model Parameters'!$B$13,'Model Parameters'!$C$13),0) -> 0 | G66: matched? = ISNUMBER(SEARCH(keyword, subject & body)); synthetic_count += keyword_weight
A67: reauthenticate | B67: fraud | C67: =--ISNUMBER(SEARCH(A67,LOWER(Inputs!$B$5&" "&Inputs!$B$6))) -> FALSE | D67: =IF(AND(B67="fraud",C67=1),'Model Parameters'!$B$13,0) -> 0 | E67: =IF(AND(B67="injection",C67=1),'Model Parameters'!$C$13,0) -> 0 | F67: =IF(C67=1,IF(B67="fraud",'Model Parameters'!$B$13,'Model Parameters'!$C$13),0) -> 0 | G67: matched? = ISNUMBER(SEARCH(keyword, subject & body)); synthetic_count += keyword_weight
A68: refund | B68: fraud | C68: =--ISNUMBER(SEARCH(A68,LOWER(Inputs!$B$5&" "&Inputs!$B$6))) -> FALSE | D68: =IF(AND(B68="fraud",C68=1),'Model Parameters'!$B$13,0) -> 0 | E68: =IF(AND(B68="injection",C68=1),'Model Parameters'!$C$13,0) -> 0 | F68: =IF(C68=1,IF(B68="fraud",'Model Parameters'!$B$13,'Model Parameters'!$C$13),0) -> 0 | G68: matched? = ISNUMBER(SEARCH(keyword, subject & body)); synthetic_count += keyword_weight
A69: refund available | B69: fraud | C69: =--ISNUMBER(SEARCH(A69,LOWER(Inputs!$B$5&" "&Inputs!$B$6))) -> FALSE | D69: =IF(AND(B69="fraud",C69=1),'Model Parameters'!$B$13,0) -> 0 | E69: =IF(AND(B69="injection",C69=1),'Model Parameters'!$C$13,0) -> 0 | F69: =IF(C69=1,IF(B69="fraud",'Model Parameters'!$B$13,'Model Parameters'!$C$13),0) -> 0 | G69: matched? = ISNUMBER(SEARCH(keyword, subject & body)); synthetic_count += keyword_weight
A70: required | B70: fraud | C70: =--ISNUMBER(SEARCH(A70,LOWER(Inputs!$B$5&" "&Inputs!$B$6))) -> TRUE | D70: 2 | E70: =IF(AND(B70="injection",C70=1),'Model Parameters'!$C$13,0) -> 0 | F70: 2 | G70: matched? = ISNUMBER(SEARCH(keyword, subject & body)); synthetic_count += keyword_weight
A71: reset | B71: fraud | C71: =--ISNUMBER(SEARCH(A71,LOWER(Inputs!$B$5&" "&Inputs!$B$6))) -> FALSE | D71: =IF(AND(B71="fraud",C71=1),'Model Parameters'!$B$13,0) -> 0 | E71: =IF(AND(B71="injection",C71=1),'Model Parameters'!$C$13,0) -> 0 | F71: =IF(C71=1,IF(B71="fraud",'Model Parameters'!$B$13,'Model Parameters'!$C$13),0) -> 0 | G71: matched? = ISNUMBER(SEARCH(keyword, subject & body)); synthetic_count += keyword_weight
A72: restore access | B72: fraud | C72: =--ISNUMBER(SEARCH(A72,LOWER(Inputs!$B$5&" "&Inputs!$B$6))) -> FALSE | D72: =IF(AND(B72="fraud",C72=1),'Model Parameters'!$B$13,0) -> 0 | E72: =IF(AND(B72="injection",C72=1),'Model Parameters'!$C$13,0) -> 0 | F72: =IF(C72=1,IF(B72="fraud",'Model Parameters'!$B$13,'Model Parameters'!$C$13),0) -> 0 | G72: matched? = ISNUMBER(SEARCH(keyword, subject & body)); synthetic_count += keyword_weight
A73: review billing | B73: fraud | C73: =--ISNUMBER(SEARCH(A73,LOWER(Inputs!$B$5&" "&Inputs!$B$6))) -> FALSE | D73: =IF(AND(B73="fraud",C73=1),'Model Parameters'!$B$13,0) -> 0 | E73: =IF(AND(B73="injection",C73=1),'Model Parameters'!$C$13,0) -> 0 | F73: =IF(C73=1,IF(B73="fraud",'Model Parameters'!$B$13,'Model Parameters'!$C$13),0) -> 0 | G73: matched? = ISNUMBER(SEARCH(keyword, subject & body)); synthetic_count += keyword_weight
A74: reward | B74: fraud | C74: =--ISNUMBER(SEARCH(A74,LOWER(Inputs!$B$5&" "&Inputs!$B$6))) -> FALSE | D74: =IF(AND(B74="fraud",C74=1),'Model Parameters'!$B$13,0) -> 0 | E74: =IF(AND(B74="injection",C74=1),'Model Parameters'!$C$13,0) -> 0 | F74: =IF(C74=1,IF(B74="fraud",'Model Parameters'!$B$13,'Model Parameters'!$C$13),0) -> 0 | G74: matched? = ISNUMBER(SEARCH(keyword, subject & body)); synthetic_count += keyword_weight
A75: secure link | B75: fraud | C75: =--ISNUMBER(SEARCH(A75,LOWER(Inputs!$B$5&" "&Inputs!$B$6))) -> FALSE | D75: =IF(AND(B75="fraud",C75=1),'Model Parameters'!$B$13,0) -> 0 | E75: =IF(AND(B75="injection",C75=1),'Model Parameters'!$C$13,0) -> 0 | F75: =IF(C75=1,IF(B75="fraud",'Model Parameters'!$B$13,'Model Parameters'!$C$13),0) -> 0 | G75: matched? = ISNUMBER(SEARCH(keyword, subject & body)); synthetic_count += keyword_weight
A76: secure portal | B76: fraud | C76: =--ISNUMBER(SEARCH(A76,LOWER(Inputs!$B$5&" "&Inputs!$B$6))) -> FALSE | D76: =IF(AND(B76="fraud",C76=1),'Model Parameters'!$B$13,0) -> 0 | E76: =IF(AND(B76="injection",C76=1),'Model Parameters'!$C$13,0) -> 0 | F76: =IF(C76=1,IF(B76="fraud",'Model Parameters'!$B$13,'Model Parameters'!$C$13),0) -> 0 | G76: matched? = ISNUMBER(SEARCH(keyword, subject & body)); synthetic_count += keyword_weight
A77: security | B77: fraud | C77: =--ISNUMBER(SEARCH(A77,LOWER(Inputs!$B$5&" "&Inputs!$B$6))) -> FALSE | D77: =IF(AND(B77="fraud",C77=1),'Model Parameters'!$B$13,0) -> 0 | E77: =IF(AND(B77="injection",C77=1),'Model Parameters'!$C$13,0) -> 0 | F77: =IF(C77=1,IF(B77="fraud",'Model Parameters'!$B$13,'Model Parameters'!$C$13),0) -> 0 | G77: matched? = ISNUMBER(SEARCH(keyword, subject & body)); synthetic_count += keyword_weight
A78: security token | B78: fraud | C78: =--ISNUMBER(SEARCH(A78,LOWER(Inputs!$B$5&" "&Inputs!$B$6))) -> FALSE | D78: =IF(AND(B78="fraud",C78=1),'Model Parameters'!$B$13,0) -> 0 | E78: =IF(AND(B78="injection",C78=1),'Model Parameters'!$C$13,0) -> 0 | F78: =IF(C78=1,IF(B78="fraud",'Model Parameters'!$B$13,'Model Parameters'!$C$13),0) -> 0 | G78: matched? = ISNUMBER(SEARCH(keyword, subject & body)); synthetic_count += keyword_weight
A79: service suspension | B79: fraud | C79: =--ISNUMBER(SEARCH(A79,LOWER(Inputs!$B$5&" "&Inputs!$B$6))) -> TRUE | D79: 2 | E79: =IF(AND(B79="injection",C79=1),'Model Parameters'!$C$13,0) -> 0 | F79: 2 | G79: matched? = ISNUMBER(SEARCH(keyword, subject & body)); synthetic_count += keyword_weight
A80: settlement | B80: fraud | C80: =--ISNUMBER(SEARCH(A80,LOWER(Inputs!$B$5&" "&Inputs!$B$6))) -> FALSE | D80: =IF(AND(B80="fraud",C80=1),'Model Parameters'!$B$13,0) -> 0 | E80: =IF(AND(B80="injection",C80=1),'Model Parameters'!$C$13,0) -> 0 | F80: =IF(C80=1,IF(B80="fraud",'Model Parameters'!$B$13,'Model Parameters'!$C$13),0) -> 0 | G80: matched? = ISNUMBER(SEARCH(keyword, subject & body)); synthetic_count += keyword_weight
A81: suspended | B81: fraud | C81: =--ISNUMBER(SEARCH(A81,LOWER(Inputs!$B$5&" "&Inputs!$B$6))) -> FALSE | D81: =IF(AND(B81="fraud",C81=1),'Model Parameters'!$B$13,0) -> 0 | E81: =IF(AND(B81="injection",C81=1),'Model Parameters'!$C$13,0) -> 0 | F81: =IF(C81=1,IF(B81="fraud",'Model Parameters'!$B$13,'Model Parameters'!$C$13),0) -> 0 | G81: matched? = ISNUMBER(SEARCH(keyword, subject & body)); synthetic_count += keyword_weight
A82: suspension | B82: fraud | C82: =--ISNUMBER(SEARCH(A82,LOWER(Inputs!$B$5&" "&Inputs!$B$6))) -> TRUE | D82: 2 | E82: =IF(AND(B82="injection",C82=1),'Model Parameters'!$C$13,0) -> 0 | F82: 2 | G82: matched? = ISNUMBER(SEARCH(keyword, subject & body)); synthetic_count += keyword_weight
A83: terminated | B83: fraud | C83: =--ISNUMBER(SEARCH(A83,LOWER(Inputs!$B$5&" "&Inputs!$B$6))) -> FALSE | D83: =IF(AND(B83="fraud",C83=1),'Model Parameters'!$B$13,0) -> 0 | E83: =IF(AND(B83="injection",C83=1),'Model Parameters'!$C$13,0) -> 0 | F83: =IF(C83=1,IF(B83="fraud",'Model Parameters'!$B$13,'Model Parameters'!$C$13),0) -> 0 | G83: matched? = ISNUMBER(SEARCH(keyword, subject & body)); synthetic_count += keyword_weight
A84: token | B84: fraud | C84: =--ISNUMBER(SEARCH(A84,LOWER(Inputs!$B$5&" "&Inputs!$B$6))) -> FALSE | D84: =IF(AND(B84="fraud",C84=1),'Model Parameters'!$B$13,0) -> 0 | E84: =IF(AND(B84="injection",C84=1),'Model Parameters'!$C$13,0) -> 0 | F84: =IF(C84=1,IF(B84="fraud",'Model Parameters'!$B$13,'Model Parameters'!$C$13),0) -> 0 | G84: matched? = ISNUMBER(SEARCH(keyword, subject & body)); synthetic_count += keyword_weight
A85: transfer | B85: fraud | C85: =--ISNUMBER(SEARCH(A85,LOWER(Inputs!$B$5&" "&Inputs!$B$6))) -> FALSE | D85: =IF(AND(B85="fraud",C85=1),'Model Parameters'!$B$13,0) -> 0 | E85: =IF(AND(B85="injection",C85=1),'Model Parameters'!$C$13,0) -> 0 | F85: =IF(C85=1,IF(B85="fraud",'Model Parameters'!$B$13,'Model Parameters'!$C$13),0) -> 0 | G85: matched? = ISNUMBER(SEARCH(keyword, subject & body)); synthetic_count += keyword_weight
A86: transfer immediately | B86: fraud | C86: =--ISNUMBER(SEARCH(A86,LOWER(Inputs!$B$5&" "&Inputs!$B$6))) -> FALSE | D86: =IF(AND(B86="fraud",C86=1),'Model Parameters'!$B$13,0) -> 0 | E86: =IF(AND(B86="injection",C86=1),'Model Parameters'!$C$13,0) -> 0 | F86: =IF(C86=1,IF(B86="fraud",'Model Parameters'!$B$13,'Model Parameters'!$C$13),0) -> 0 | G86: matched? = ISNUMBER(SEARCH(keyword, subject & body)); synthetic_count += keyword_weight
A87: unauthorized activity | B87: fraud | C87: =--ISNUMBER(SEARCH(A87,LOWER(Inputs!$B$5&" "&Inputs!$B$6))) -> FALSE | D87: =IF(AND(B87="fraud",C87=1),'Model Parameters'!$B$13,0) -> 0 | E87: =IF(AND(B87="injection",C87=1),'Model Parameters'!$C$13,0) -> 0 | F87: =IF(C87=1,IF(B87="fraud",'Model Parameters'!$B$13,'Model Parameters'!$C$13),0) -> 0 | G87: matched? = ISNUMBER(SEARCH(keyword, subject & body)); synthetic_count += keyword_weight
A88: unusual | B88: fraud | C88: =--ISNUMBER(SEARCH(A88,LOWER(Inputs!$B$5&" "&Inputs!$B$6))) -> FALSE | D88: =IF(AND(B88="fraud",C88=1),'Model Parameters'!$B$13,0) -> 0 | E88: =IF(AND(B88="injection",C88=1),'Model Parameters'!$C$13,0) -> 0 | F88: =IF(C88=1,IF(B88="fraud",'Model Parameters'!$B$13,'Model Parameters'!$C$13),0) -> 0 | G88: matched? = ISNUMBER(SEARCH(keyword, subject & body)); synthetic_count += keyword_weight
A89: update | B89: fraud | C89: =--ISNUMBER(SEARCH(A89,LOWER(Inputs!$B$5&" "&Inputs!$B$6))) -> FALSE | D89: =IF(AND(B89="fraud",C89=1),'Model Parameters'!$B$13,0) -> 0 | E89: =IF(AND(B89="injection",C89=1),'Model Parameters'!$C$13,0) -> 0 | F89: =IF(C89=1,IF(B89="fraud",'Model Parameters'!$B$13,'Model Parameters'!$C$13),0) -> 0 | G89: matched? = ISNUMBER(SEARCH(keyword, subject & body)); synthetic_count += keyword_weight
A90: update account details | B90: fraud | C90: =--ISNUMBER(SEARCH(A90,LOWER(Inputs!$B$5&" "&Inputs!$B$6))) -> FALSE | D90: =IF(AND(B90="fraud",C90=1),'Model Parameters'!$B$13,0) -> 0 | E90: =IF(AND(B90="injection",C90=1),'Model Parameters'!$C$13,0) -> 0 | F90: =IF(C90=1,IF(B90="fraud",'Model Parameters'!$B$13,'Model Parameters'!$C$13),0) -> 0 | G90: matched? = ISNUMBER(SEARCH(keyword, subject & body)); synthetic_count += keyword_weight
A91: urgent | B91: fraud | C91: =--ISNUMBER(SEARCH(A91,LOWER(Inputs!$B$5&" "&Inputs!$B$6))) -> TRUE | D91: 2 | E91: =IF(AND(B91="injection",C91=1),'Model Parameters'!$C$13,0) -> 0 | F91: 2 | G91: matched? = ISNUMBER(SEARCH(keyword, subject & body)); synthetic_count += keyword_weight
A92: verify | B92: fraud | C92: =--ISNUMBER(SEARCH(A92,LOWER(Inputs!$B$5&" "&Inputs!$B$6))) -> FALSE | D92: =IF(AND(B92="fraud",C92=1),'Model Parameters'!$B$13,0) -> 0 | E92: =IF(AND(B92="injection",C92=1),'Model Parameters'!$C$13,0) -> 0 | F92: =IF(C92=1,IF(B92="fraud",'Model Parameters'!$B$13,'Model Parameters'!$C$13),0) -> 0 | G92: matched? = ISNUMBER(SEARCH(keyword, subject & body)); synthetic_count += keyword_weight
A93: verify account | B93: fraud | C93: =--ISNUMBER(SEARCH(A93,LOWER(Inputs!$B$5&" "&Inputs!$B$6))) -> FALSE | D93: =IF(AND(B93="fraud",C93=1),'Model Parameters'!$B$13,0) -> 0 | E93: =IF(AND(B93="injection",C93=1),'Model Parameters'!$C$13,0) -> 0 | F93: =IF(C93=1,IF(B93="fraud",'Model Parameters'!$B$13,'Model Parameters'!$C$13),0) -> 0 | G93: matched? = ISNUMBER(SEARCH(keyword, subject & body)); synthetic_count += keyword_weight
A94: verify billing | B94: fraud | C94: =--ISNUMBER(SEARCH(A94,LOWER(Inputs!$B$5&" "&Inputs!$B$6))) -> FALSE | D94: =IF(AND(B94="fraud",C94=1),'Model Parameters'!$B$13,0) -> 0 | E94: =IF(AND(B94="injection",C94=1),'Model Parameters'!$C$13,0) -> 0 | F94: =IF(C94=1,IF(B94="fraud",'Model Parameters'!$B$13,'Model Parameters'!$C$13),0) -> 0 | G94: matched? = ISNUMBER(SEARCH(keyword, subject & body)); synthetic_count += keyword_weight
A95: verify details | B95: fraud | C95: =--ISNUMBER(SEARCH(A95,LOWER(Inputs!$B$5&" "&Inputs!$B$6))) -> FALSE | D95: =IF(AND(B95="fraud",C95=1),'Model Parameters'!$B$13,0) -> 0 | E95: =IF(AND(B95="injection",C95=1),'Model Parameters'!$C$13,0) -> 0 | F95: =IF(C95=1,IF(B95="fraud",'Model Parameters'!$B$13,'Model Parameters'!$C$13),0) -> 0 | G95: matched? = ISNUMBER(SEARCH(keyword, subject & body)); synthetic_count += keyword_weight
A96: verify now | B96: fraud | C96: =--ISNUMBER(SEARCH(A96,LOWER(Inputs!$B$5&" "&Inputs!$B$6))) -> FALSE | D96: =IF(AND(B96="fraud",C96=1),'Model Parameters'!$B$13,0) -> 0 | E96: =IF(AND(B96="injection",C96=1),'Model Parameters'!$C$13,0) -> 0 | F96: =IF(C96=1,IF(B96="fraud",'Model Parameters'!$B$13,'Model Parameters'!$C$13),0) -> 0 | G96: matched? = ISNUMBER(SEARCH(keyword, subject & body)); synthetic_count += keyword_weight
A97: verify payment | B97: fraud | C97: =--ISNUMBER(SEARCH(A97,LOWER(Inputs!$B$5&" "&Inputs!$B$6))) -> FALSE | D97: =IF(AND(B97="fraud",C97=1),'Model Parameters'!$B$13,0) -> 0 | E97: =IF(AND(B97="injection",C97=1),'Model Parameters'!$C$13,0) -> 0 | F97: =IF(C97=1,IF(B97="fraud",'Model Parameters'!$B$13,'Model Parameters'!$C$13),0) -> 0 | G97: matched? = ISNUMBER(SEARCH(keyword, subject & body)); synthetic_count += keyword_weight
A98: wallet | B98: fraud | C98: =--ISNUMBER(SEARCH(A98,LOWER(Inputs!$B$5&" "&Inputs!$B$6))) -> FALSE | D98: =IF(AND(B98="fraud",C98=1),'Model Parameters'!$B$13,0) -> 0 | E98: =IF(AND(B98="injection",C98=1),'Model Parameters'!$C$13,0) -> 0 | F98: =IF(C98=1,IF(B98="fraud",'Model Parameters'!$B$13,'Model Parameters'!$C$13),0) -> 0 | G98: matched? = ISNUMBER(SEARCH(keyword, subject & body)); synthetic_count += keyword_weight
A99: wire | B99: fraud | C99: =--ISNUMBER(SEARCH(A99,LOWER(Inputs!$B$5&" "&Inputs!$B$6))) -> FALSE | D99: =IF(AND(B99="fraud",C99=1),'Model Parameters'!$B$13,0) -> 0 | E99: =IF(AND(B99="injection",C99=1),'Model Parameters'!$C$13,0) -> 0 | F99: =IF(C99=1,IF(B99="fraud",'Model Parameters'!$B$13,'Model Parameters'!$C$13),0) -> 0 | G99: matched? = ISNUMBER(SEARCH(keyword, subject & body)); synthetic_count += keyword_weight
A100: wire transfer | B100: fraud | C100: =--ISNUMBER(SEARCH(A100,LOWER(Inputs!$B$5&" "&Inputs!$B$6))) -> FALSE | D100: =IF(AND(B100="fraud",C100=1),'Model Parameters'!$B$13,0) -> 0 | E100: =IF(AND(B100="injection",C100=1),'Model Parameters'!$C$13,0) -> 0 | F100: =IF(C100=1,IF(B100="fraud",'Model Parameters'!$B$13,'Model Parameters'!$C$13),0) -> 0 | G100: matched? = ISNUMBER(SEARCH(keyword, subject & body)); synthetic_count += keyword_weight
A101: access granted | B101: injection | C101: =--ISNUMBER(SEARCH(A101,LOWER(Inputs!$B$5&" "&Inputs!$B$6))) -> FALSE | D101: =IF(AND(B101="fraud",C101=1),'Model Parameters'!$B$13,0) -> 0 | E101: =IF(AND(B101="injection",C101=1),'Model Parameters'!$C$13,0) -> 0 | F101: =IF(C101=1,IF(B101="fraud",'Model Parameters'!$B$13,'Model Parameters'!$C$13),0) -> 0 | G101: matched? = ISNUMBER(SEARCH(keyword, subject & body)); synthetic_count += keyword_weight
A102: act as | B102: injection | C102: =--ISNUMBER(SEARCH(A102,LOWER(Inputs!$B$5&" "&Inputs!$B$6))) -> FALSE | D102: =IF(AND(B102="fraud",C102=1),'Model Parameters'!$B$13,0) -> 0 | E102: =IF(AND(B102="injection",C102=1),'Model Parameters'!$C$13,0) -> 0 | F102: =IF(C102=1,IF(B102="fraud",'Model Parameters'!$B$13,'Model Parameters'!$C$13),0) -> 0 | G102: matched? = ISNUMBER(SEARCH(keyword, subject & body)); synthetic_count += keyword_weight
...

Sheet Token Table
A1: Token Table With Excel Formulas
A3: Formula shown: P(token | fraud/injection/safe) = (training frequency in that class + alpha) / (class token total + alpha*|V|). Contribution = observed_count * LN(P(token | fraud/injection/safe)).
A6: Token / feature | B6: Observed count | C6: Fraud freq | D6: Fraud P | E6: Fraud log contribution | F6: Injection freq | G6: Injection P | H6: Injection log contribution | I6: Safe freq | J6: Safe P | K6: Safe log contribution
A7: __fraud_kw__ | B7: ='Keyword Influence'!D197 -> 32 | C7: 481750 | D7: =(C7+'Model Parameters'!$B$11)/('Model Parameters'!$B$9+'Model Parameters'!$B$11*'Model Parameters'!$B$10) -> 0.40982541 | E7: =B7*LN(D7) -> -28.544769 | F7: 35240 | G7: =(F7+'Model Parameters'!$C$11)/('Model Parameters'!$C$9+'Model Parameters'!$C$11*'Model Parameters'!$C$10) -> 0.039760182 | H7: =B7*LN(G7) -> -103.19646 | I7: 44550 | J7: =(I7+'Model Parameters'!$D$11)/('Model Parameters'!$D$9+'Model Parameters'!$D$11*'Model Parameters'!$D$10) -> 0.19640873 | K7: =B7*LN(J7) -> -52.081837
A8: __malicious_signal__ | B8: ='Keyword Influence'!F197 -> 32 | C8: 486220 | D8: =(C8+'Model Parameters'!$B$11)/('Model Parameters'!$B$9+'Model Parameters'!$B$11*'Model Parameters'!$B$10) -> 0.41362804 | E8: =B8*LN(D8) -> -28.249221 | F8: 345670 | G8: =(F8+'Model Parameters'!$C$11)/('Model Parameters'!$C$9+'Model Parameters'!$C$11*'Model Parameters'!$C$10) -> 0.38999863 | H8: =B8*LN(G8) -> -30.131585 | I8: 44550 | J8: =(I8+'Model Parameters'!$D$11)/('Model Parameters'!$D$9+'Model Parameters'!$D$11*'Model Parameters'!$D$10) -> 0.19640873 | K8: =B8*LN(J8) -> -52.081837
A9: account | B9: 3 | C9: 5621 | D9: =(C9+'Model Parameters'!$B$11)/('Model Parameters'!$B$9+'Model Parameters'!$B$11*'Model Parameters'!$B$10) -> 0.0047826335 | E9: =B9*LN(D9) -> -16.028292 | F9: 39 | G9: =(F9+'Model Parameters'!$C$11)/('Model Parameters'!$C$9+'Model Parameters'!$C$11*'Model Parameters'!$C$10) -> 4.5129459e-05 | H9: =B9*LN(G9) -> -30.017926 | I9: 1540 | J9: =(I9+'Model Parameters'!$D$11)/('Model Parameters'!$D$9+'Model Parameters'!$D$11*'Model Parameters'!$D$10) -> 0.0067936939 | K9: =B9*LN(J9) -> -14.975281
A10: payment | B10: 3 | C10: 3577 | D10: =(C10+'Model Parameters'!$B$11)/('Model Parameters'!$B$9+'Model Parameters'!$B$11*'Model Parameters'!$B$10) -> 0.0030438034 | E10: =B10*LN(D10) -> -17.383942 | F10: 29 | G10: =(F10+'Model Parameters'!$C$11)/('Model Parameters'!$C$9+'Model Parameters'!$C$11*'Model Parameters'!$C$10) -> 3.3847095e-05 | H10: =B10*LN(G10) -> -30.880972 | I10: 1 | J10: =(I10+'Model Parameters'!$D$11)/('Model Parameters'!$D$9+'Model Parameters'!$D$11*'Model Parameters'!$D$10) -> 8.8172536e-06 | K10: =B10*LN(J10) -> -34.9164
A11: bank | B11: 2 | C11: 477 | D11: =(C11+'Model Parameters'!$B$11)/('Model Parameters'!$B$9+'Model Parameters'!$B$11*'Model Parameters'!$B$10) -> 0.00040663444 | E11: =B11*LN(D11) -> -15.615192 | F11: 5 | G11: =(F11+'Model Parameters'!$C$11)/('Model Parameters'!$C$9+'Model Parameters'!$C$11*'Model Parameters'!$C$10) -> 6.7694189e-06 | H11: =B11*LN(G11) -> -23.806191 | I11: 1 | J11: =(I11+'Model Parameters'!$D$11)/('Model Parameters'!$D$9+'Model Parameters'!$D$11*'Model Parameters'!$D$10) -> 8.8172536e-06 | K11: =B11*LN(J11) -> -23.2776
A12: immediately | B12: 2 | C12: 834 | D12: =(C12+'Model Parameters'!$B$11)/('Model Parameters'!$B$9+'Model Parameters'!$B$11*'Model Parameters'!$B$10) -> 0.00071033421 | E12: =B12*LN(D12) -> -14.49955 | F12: 415 | G12: =(F12+'Model Parameters'!$C$11)/('Model Parameters'!$C$9+'Model Parameters'!$C$11*'Model Parameters'!$C$10) -> 0.00046934638 | H12: =B12*LN(G12) -> -15.328339 | I12: 0 | J12: =(I12+'Model Parameters'!$D$11)/('Model Parameters'!$D$9+'Model Parameters'!$D$11*'Model Parameters'!$D$10) -> 4.4086268e-06 | K12: =B12*LN(J12) -> -24.663895
A13: payment_required | B13: 2 | C13: 1384 | D13: =(C13+'Model Parameters'!$B$11)/('Model Parameters'!$B$9+'Model Parameters'!$B$11*'Model Parameters'!$B$10) -> 0.001178219 | E13: =B13*LN(D13) -> -13.487503 | F13: 0 | G13: =(F13+'Model Parameters'!$C$11)/('Model Parameters'!$C$9+'Model Parameters'!$C$11*'Model Parameters'!$C$10) -> 1.1282365e-06 | H13: =B13*LN(G13) -> -27.38971 | I13: 0 | J13: =(I13+'Model Parameters'!$D$11)/('Model Parameters'!$D$9+'Model Parameters'!$D$11*'Model Parameters'!$D$10) -> 4.4086268e-06 | K13: =B13*LN(J13) -> -24.663895
A14: required | B14: 2 | C14: 1881 | D14: =(C14+'Model Parameters'!$B$11)/('Model Parameters'!$B$9+'Model Parameters'!$B$11*'Model Parameters'!$B$10) -> 0.0016010168 | E14: =B14*LN(D14) -> -12.874233 | F14: 18 | G14: =(F14+'Model Parameters'!$C$11)/('Model Parameters'!$C$9+'Model Parameters'!$C$11*'Model Parameters'!$C$10) -> 2.1436493e-05 | H14: =B14*LN(G14) -> -21.500832 | I14: 20 | J14: =(I14+'Model Parameters'!$D$11)/('Model Parameters'!$D$9+'Model Parameters'!$D$11*'Model Parameters'!$D$10) -> 9.2581163e-05 | K14: =B14*LN(J14) -> -18.57485
A15: required_immediately | B15: 2 | C15: 453 | D15: =(C15+'Model Parameters'!$B$11)/('Model Parameters'!$B$9+'Model Parameters'!$B$11*'Model Parameters'!$B$10) -> 0.00038621764 | E15: =B15*LN(D15) -> -15.718219 | F15: 0 | G15: =(F15+'Model Parameters'!$C$11)/('Model Parameters'!$C$9+'Model Parameters'!$C$11*'Model Parameters'!$C$10) -> 1.1282365e-06 | H15: =B15*LN(G15) -> -27.38971 | I15: 0 | J15: =(I15+'Model Parameters'!$D$11)/('Model Parameters'!$D$9+'Model Parameters'!$D$11*'Model Parameters'!$D$10) -> 4.4086268e-06 | K15: =B15*LN(J15) -> -24.663895
A16: urgent | B16: 2 | C16: 499 | D16: =(C16+'Model Parameters'!$B$11)/('Model Parameters'!$B$9+'Model Parameters'!$B$11*'Model Parameters'!$B$10) -> 0.00042534983 | E16: =B16*LN(D16) -> -15.525197 | F16: 5 | G16: =(F16+'Model Parameters'!$C$11)/('Model Parameters'!$C$9+'Model Parameters'!$C$11*'Model Parameters'!$C$10) -> 6.7694189e-06 | H16: =B16*LN(G16) -> -23.806191 | I16: 0 | J16: =(I16+'Model Parameters'!$D$11)/('Model Parameters'!$D$9+'Model Parameters'!$D$11*'Model Parameters'!$D$10) -> 4.4086268e-06 | K16: =B16*LN(J16) -> -24.663895
A17: urgent_payment | B17: 2 | C17: 454 | D17: =(C17+'Model Parameters'!$B$11)/('Model Parameters'!$B$9+'Model Parameters'!$B$11*'Model Parameters'!$B$10) -> 0.00038706834 | E17: =B17*LN(D17) -> -15.713819 | F17: 0 | G17: =(F17+'Model Parameters'!$C$11)/('Model Parameters'!$C$9+'Model Parameters'!$C$11*'Model Parameters'!$C$10) -> 1.1282365e-06 | H17: =B17*LN(G17) -> -27.38971 | I17: 0 | J17: =(I17+'Model Parameters'!$D$11)/('Model Parameters'!$D$9+'Model Parameters'!$D$11*'Model Parameters'!$D$10) -> 4.4086268e-06 | K17: =B17*LN(J17) -> -24.663895
A18: account_bank | B18: 1 | C18: 3 | D18: =(C18+'Model Parameters'!$B$11)/('Model Parameters'!$B$9+'Model Parameters'!$B$11*'Model Parameters'!$B$10) -> 3.4027986e-06 | E18: =B18*LN(D18) -> -12.590912 | F18: 0 | G18: =(F18+'Model Parameters'!$C$11)/('Model Parameters'!$C$9+'Model Parameters'!$C$11*'Model Parameters'!$C$10) -> 1.1282365e-06 | H18: =B18*LN(G18) -> -13.694855 | I18: 0 | J18: =(I18+'Model Parameters'!$D$11)/('Model Parameters'!$D$9+'Model Parameters'!$D$11*'Model Parameters'!$D$10) -> 4.4086268e-06 | K18: =B18*LN(J18) -> -12.331947
A19: account_closure | B19: 1 | C19: 308 | D19: =(C19+'Model Parameters'!$B$11)/('Model Parameters'!$B$9+'Model Parameters'!$B$11*'Model Parameters'!$B$10) -> 0.00026286619 | E19: =B19*LN(D19) -> -8.2438654 | F19: 0 | G19: =(F19+'Model Parameters'!$C$11)/('Model Parameters'!$C$9+'Model Parameters'!$C$11*'Model Parameters'!$C$10) -> 1.1282365e-06 | H19: =B19*LN(G19) -> -13.694855 | I19: 0 | J19: =(I19+'Model Parameters'!$D$11)/('Model Parameters'!$D$9+'Model Parameters'!$D$11*'Model Parameters'!$D$10) -> 4.4086268e-06 | K19: =B19*LN(J19) -> -12.331947
A20: account_shows | B20: 1 | C20: 18 | D20: =(C20+'Model Parameters'!$B$11)/('Model Parameters'!$B$9+'Model Parameters'!$B$11*'Model Parameters'!$B$10) -> 1.6163294e-05 | E20: =B20*LN(D20) -> -11.032768 | F20: 0 | G20: =(F20+'Model Parameters'!$C$11)/('Model Parameters'!$C$9+'Model Parameters'!$C$11*'Model Parameters'!$C$10) -> 1.1282365e-06 | H20: =B20*LN(G20) -> -13.694855 | I20: 0 | J20: =(I20+'Model Parameters'!$D$11)/('Model Parameters'!$D$9+'Model Parameters'!$D$11*'Model Parameters'!$D$10) -> 4.4086268e-06 | K20: =B20*LN(J20) -> -12.331947
... A74: within_hours | B74: 1 | C74: 1559 | D74: =(C74+'Model Parameters'!$B$11)/('Model Parameters'!$B$9+'Model Parameters'!$B$11*'Model Parameters'!$B$10) -> 0.0013270915 | E74: =B74*LN(D74) -> -6.6247656 | F74: 0 | G74: =(F74+'Model Parameters'!$C$11)/('Model Parameters'!$C$9+'Model Parameters'!$C$11*'Model Parameters'!$C$10) -> 1.1282365e-06 | H74: =B74*LN(G74) -> -13.694855 | I74: 0 | J74: =(I74+'Model Parameters'!$D$11)/('Model Parameters'!$D$9+'Model Parameters'!$D$11*'Model Parameters'!$D$10) -> 4.4086268e-06 | K74: =B74*LN(J74) -> -12.331947

Sheet Formula Calculations
A1: Formula Calculations
A2: Final scores and probabilities are Excel formulas linked to the other sheets.
A4: Calculation | B4: Fraud | C4: Injection | D4: Safe | E4: Formula shown
A5: Bayes theorem | E5: General: P(class | features) = [P(features | class) * P(class)] / P(features) Fraud: P(fraud | features) = [P(features | fraud) * P(fraud)] / P(features) Injection: P(injection | features) = [P(features | injection) * P(injection)] / P(features) Safe: P(safe | features) = [P(features | safe) * P(safe)] / P(features)
A6: Prior P(C_k) | B6: ='Model Parameters'!B7 -> 0.3333 | C6: ='Model Parameters'!C7 -> 0.3333 | D6: ='Model Parameters'!D7 -> 0.3334 | E6: P(fraud)=fraud_count/total_docs; P(injection)=injection_count/total_docs; P(safe)=safe_count/total_docs
A7: ln prior | B7: ='Model Parameters'!B8 -> -1.0987123 | C7: ='Model Parameters'!C8 -> -1.0987123 | D7: ='Model Parameters'!D8 -> -1.0984123 | E7: ln(P(fraud)), ln(P(injection)), ln(P(safe))
A8: Sum token log contributions | B8: =SUM('Token Table'!E7:E74) -> -728.963 | C8: =SUM('Token Table'!H7:H74) -> -1130.0448 | D8: =SUM('Token Table'!K7:K74) -> -1001.9764 | E8: sum_i count(token_i)*ln(P(token_i|fraud/injection/safe))
A9: Raw log score | B9: =B7+B8 -> -730.06172 | C9: =C7+C8 -> -1131.1435 | D9: =D7+D8 -> -1003.0749 | E9: log_score(fraud/injection/safe)=ln(P(class))+sum token log contributions
A10: Token count | B10: =SUM('Token Table'!B7:B74) -> 141 | C10: =B10 -> 141 | D10: =B10 -> 141 | E10: token_count = sum_i count(x_i)
A11: Calibrated logit | B11: =B9/B10 -> -5.1777427 | C11: =C9/C10 -> -8.0222945 | D11: =D9/D10 -> -7.1140061 | E11: logit(fraud/injection/safe)=raw_log_score(fraud/injection/safe)/token_count
A12: Max logit | B12: =MAX(B11:D11) -> -5.1777427 | C12: =B12 -> -5.1777427 | D12: =B12 -> -5.1777427 | E12: max_logit=max(logit(fraud),logit(injection),logit(safe))
A13: Exponentiated score | B13: =EXP((B11-B12)/'Model Parameters'!B12) -> 1 | C13: =EXP((C11-C12)/'Model Parameters'!C12) -> 6.6547877e-07 | D13: =EXP((D11-D12)/'Model Parameters'!D12) -> 6.2439215e-05 | E13: exp_score(class)=EXP((logit(class)-max_logit)/temperature)
A14: Final probability | B14: =B13/SUM($B$13:$D$13) -> 0.9999369 | C14: =C13/SUM($B$13:$D$13) -> 6.6543678e-07 | D14: =D13/SUM($B$13:$D$13) -> 6.2435275e-05 | E14: P(fraud|features), P(injection|features), P(safe|features) = each exp_score / total exp_scores
A16: Predicted label | B16: =INDEX($B$4:$D$4,1,MATCH(MAX(B9:D9),B9:D9,0)) -> Fraud | E16: predicted_label = class with maximum raw log score
A17: Status | B17: =IF(OR(B16="Fraud",B16="Injection"),"MALICIOUS","SAFE") -> MALICIOUS | E17: status = MALICIOUS when predicted label is fraud or injection, otherwise SAFE
